sematic/__init__.py
sematic/abstract_function.py
sematic/abstract_future.py
sematic/abstract_plugin.py
sematic/abstract_system_metric.py
sematic/api_client.py
sematic/client.py
sematic/conftest.py
sematic/container_images.py
sematic/function.py
sematic/future.py
sematic/future_context.py
sematic/graph.py
sematic/log_reader.py
sematic/logs.py
sematic/resolver.py
sematic/retry_settings.py
sematic/runner.py
sematic/torch_patch.py
sematic/versions.py
sematic/api/__init__.py
sematic/api/app.py
sematic/api/server.py
sematic/api/endpoints/__init__.py
sematic/api/endpoints/artifacts.py
sematic/api/endpoints/auth.py
sematic/api/endpoints/edges.py
sematic/api/endpoints/events.py
sematic/api/endpoints/external_resources.py
sematic/api/endpoints/meta.py
sematic/api/endpoints/metrics.py
sematic/api/endpoints/notes.py
sematic/api/endpoints/organizations.py
sematic/api/endpoints/organizations_users.py
sematic/api/endpoints/payloads.py
sematic/api/endpoints/request_parameters.py
sematic/api/endpoints/resolutions.py
sematic/api/endpoints/runs.py
sematic/api/endpoints/storage.py
sematic/api/endpoints/users.py
sematic/caching/__init__.py
sematic/caching/caching.py
sematic/caching/git.py
sematic/cli/__init__.py
sematic/cli/cancel.py
sematic/cli/clean.py
sematic/cli/cli.py
sematic/cli/examples_utils.py
sematic/cli/github.py
sematic/cli/logs.py
sematic/cli/main.py
sematic/cli/migrate.py
sematic/cli/new.py
sematic/cli/process_utils.py
sematic/cli/run.py
sematic/cli/settings.py
sematic/cli/start.py
sematic/cli/stop.py
sematic/cli/version.py
sematic/config/__init__.py
sematic/config/config.py
sematic/config/config_dir.py
sematic/config/server_settings.py
sematic/config/settings.py
sematic/config/user_settings.py
sematic/db/__init__.py
sematic/db/db.py
sematic/db/migrate.py
sematic/db/migration_utils.py
sematic/db/queries.py
sematic/db/schema.sql.sqlite
sematic/db/migrations/20220424062956_create_runs_table.sql
sematic/db/migrations/20220514015440_create_artifacts_table.sql
sematic-0.41.0.dist-info/LICENSE
sematic-0.41.0.dist-info/METADATA
sematic-0.41.0.dist-info/WHEEL
sematic-0.41.0.dist-info/entry_points.txt
sematic-0.41.0.dist-info/top_level.txt
sematic-0.41.0.dist-info/RECORD
