Metadata-Version: 2.2
Name: sematic
Version: 0.41.0
Summary: Sematic ML orchestration tool
Requires-Python: <3.14,>=3.9
License-File: LICENSE
Requires-Dist: ipython==8.2.0
Requires-Dist: setuptools==58.1.0
Requires-Dist: SQLAlchemy>=2.0
Requires-Dist: psycopg2-binary>=2.9.5
Requires-Dist: pyyaml>=6.0.1
Requires-Dist: python-magic>=0.4.27
Requires-Dist: git-python>=1.0.3
Requires-Dist: docker>=6.0.0
Requires-Dist: websocket-client>=1.5.1
Requires-Dist: python-socketio>=5.7.2
Requires-Dist: flask>=2.2.2
Requires-Dist: flask-cors>=3.0.10
Requires-Dist: cloudpickle>=2.2.1
Requires-Dist: requests>=2.28.2
Requires-Dist: werkzeug>=2.2.3
Requires-Dist: python-dateutil>=2.8.2
Requires-Dist: starlette>=0.25.0
Requires-Dist: google-auth>=2.16.0
Requires-Dist: uvicorn[standard]>=0.20.0
Requires-Dist: asgiref>=3.7.2
Requires-Dist: click>=8.1.3
Requires-Dist: kubernetes>=25.3.0
Requires-Dist: boto3>=1.26.82
Requires-Dist: google-cloud-storage>=2.10.0
Requires-Dist: types-google-cloud-ndb>=2.2.0.0
Provides-Extra: examples
Requires-Dist: snowflake-connector-python==3.12.4; python_version < "3.13" and extra == "examples"
Requires-Dist: pyOpenSSL>=23.0.0; extra == "examples"
Requires-Dist: pyarrow>=12.0.0; python_version < "3.13" and extra == "examples"
Requires-Dist: python-magic==0.4.27; extra == "examples"
Requires-Dist: torch>=1.13.1; python_version < "3.13" and extra == "examples"
Requires-Dist: torchvision>=0.14.1; python_version < "3.13" and extra == "examples"
Requires-Dist: pytorch-lightning>=1.6.5; python_version < "3.13" and extra == "examples"
Requires-Dist: ray-lightning>=0.3.0; python_version < "3.13" and extra == "examples"
Requires-Dist: plotly==5.13.0; python_version < "3.13" and extra == "examples"
Requires-Dist: pandas>=1.5.3; python_version < "3.13" and extra == "examples"
Requires-Dist: seaborn>=0.12.2; python_version < "3.13" and extra == "examples"
Requires-Dist: matplotlib>=3.7.0; python_version < "3.13" and extra == "examples"
Requires-Dist: statsmodels>=0.13.5; python_version < "3.13" and extra == "examples"
Requires-Dist: scikit-learn>=1.2.1; python_version < "3.13" and extra == "examples"
Requires-Dist: numpy>=1.24.0; python_version < "3.13" and extra == "examples"
Requires-Dist: xgboost>=1.7.3; python_version < "3.13" and extra == "examples"
Requires-Dist: accelerate==0.19.0; python_version < "3.13" and extra == "examples"
Requires-Dist: datasets>=2.12.0; python_version < "3.13" and extra == "examples"
Requires-Dist: huggingface-hub>=0.14.1; extra == "examples"
Requires-Dist: peft>=0.3.0; python_version < "3.13" and extra == "examples"
Requires-Dist: transformers>=4.29.2; python_version < "3.13" and extra == "examples"
Requires-Dist: gradio>=3.35.2; python_version < "3.13" and extra == "examples"
Requires-Dist: trafilatura>=1.6.0; extra == "examples"
Requires-Dist: cohere>=4.9.0; extra == "examples"
Requires-Dist: openai>=0.27.8; extra == "examples"
Provides-Extra: ray
Requires-Dist: ray[air,default]>=2.3.0; python_version < "3.13" and extra == "ray"
Provides-Extra: all
Requires-Dist: ray[air,default]>=2.3.0; python_version < "3.13" and extra == "all"
